setup.py
caipyrus/__init__.py
caipyrus/scribe.py
caipyrus.egg-info/PKG-INFO
caipyrus.egg-info/SOURCES.txt
caipyrus.egg-info/dependency_links.txt
caipyrus.egg-info/top_level.txt
caipyrus.egg-info/zip-safe
tools/render_osmdb.py