Metadata-Version: 1.0
Name: caipyrus
Version: 0.2
Summary: Cairo based procedural rendering tool.
Home-page: http://github.com/ninowalker/caipyrus/tree/master
Author: Nino Walker
Author-email: nino@ni-no.info
License: BSD
Keywords: OSM OpenStreetMap GTFS routing transit
Platform: UNKNOWN
